{
  "parent": "block/block",
  "textures": {
    "particle": "#side"
  },
  "elements": [
    {
      "from": [1, 1, 1],
      "to": [15, 15, 15],
      "shade": false,
      "faces": {
        "down": { "texture": "#side", "cullface": "down"},
        "up": { "texture": "#side", "cullface": "up"},
        "north": { "texture": "#side", "cullface": "north"},
        "south": { "texture": "#side", "cullface": "south"},
        "east": { "texture": "#side", "cullface": "east"},
        "west": { "texture": "#side", "cullface": "west"}
      }
    },
    {
      "from": [0, 0, 0],
      "to": [2, 2, 2],
      "shade": false,
      "faces": {
        "down": { "texture": "#side", "cullface": "down"},
        "up": { "texture": "#side"},
        "north": { "texture": "#side", "cullface": "north"},
        "south": { "texture": "#side"},
        "east": { "texture": "#side"},
        "west": { "texture": "#side", "cullface": "west"}
      }
    }
  ]
}
